[
  {
    "name": "ADS_Twitter_1",
    "browser_mode": "ads",
    "adspower_profile_id": "ваш_id",
    "login_method": "twitter"
  },

  {
    "name": "ADS_Google_1",
    "browser_mode": "ads",
    "adspower_profile_id": "ваш_id",
    "login_method": "google"
  },

  {
    "name": "Chrome_Google_Auto",
    "browser_mode": "chrome",
    "proxy": "",
    "remote_debugging_port": 9222,
    "login_method": "google",
    "google_email": "example@gmail.com",
    "google_password": "example_password"
  },

  {
    "name": "Chrome_Google_Manual",
    "browser_mode": "chrome",
    "proxy": "",
    "remote_debugging_port": 9223,
    "login_method": "google",
    "google_email": "",
    "google_password": ""
  },

  {
    "name": "Chrome_Twitter_1",
    "browser_mode": "chrome",
    "proxy": "",
    "remote_debugging_port": 9224,
    "login_method": "twitter",
    "cookies": "cookies/account1_cookies.json"
  }
]
